<?xml version="1.0" encoding="Windows-1252" ?>
<NotepadPlus>
    <LexerStyles>
        <LexerType name="c" desc="C" ext="">
            <WordsStyle name="PREPROCESSOR" styleID="9" fgColor="804000" bgColor="FFFFFF" fontName="" fontStyle="0" fontSize="" />
            <WordsStyle name="DEFAULT" styleID="11" fgColor="000000" bgColor="FFFFFF" fontName="" fontStyle="0" fontSize="" />
            <WordsStyle name="INSTRUCTION WORD" styleID="5" fgColor="0000FF" bgColor="FFFFFF" fontName="" fontStyle="1" fontSize="" keywordClass="instre1" />
            <WordsStyle name="TYPE WORD" styleID="16" fgColor="8000FF" bgColor="FFFFFF" fontName="" fontStyle="0" fontSize="" keywordClass="type1" />
            <WordsStyle name="NUMBER" styleID="4" fgColor="FF8000" bgColor="FFFFFF" fontName="" fontStyle="0" fontSize="" />
            <WordsStyle name="STRING" styleID="6" fgColor="808080" bgColor="FFFFFF" fontName="" fontStyle="0" fontSize="" />
            <WordsStyle name="CHARACTER" styleID="7" fgColor="808080" bgColor="FFFFFF" fontName="" fontStyle="0" fontSize="" />
            <WordsStyle name="OPERATOR" styleID="10" fgColor="000080" bgColor="FFFFFF" fontName="" fontStyle="1" fontSize="" />
            <WordsStyle name="VERBATIM" styleID="13" fgColor="000000" bgColor="FFFFFF" fontName="" fontStyle="0" fontSize="" />
            <WordsStyle name="REGEX" styleID="14" fgColor="000000" bgColor="FFFFFF" fontName="" fontStyle="1" fontSize="" />
            <WordsStyle name="COMMENT" styleID="1" fgColor="008000" bgColor="FFFFFF" fontName="" fontStyle="0" fontSize="" />
            <WordsStyle name="COMMENT LINE" styleID="2" fgColor="008000" bgColor="FFFFFF" fontName="" fontStyle="0" fontSize="" />
            <WordsStyle name="COMMENT DOC" styleID="3" fgColor="008080" bgColor="FFFFFF" fontName="" fontStyle="0" fontSize="" />
            <WordsStyle name="COMMENT LINE DOC" styleID="15" fgColor="008080" bgColor="FFFFFF" fontName="" fontStyle="0" fontSize="" />
            <WordsStyle name="COMMENT DOC KEYWORD" styleID="17" fgColor="008080" bgColor="FFFFFF" fontName="" fontStyle="1" fontSize="" />
            <WordsStyle name="COMMENT DOC KEYWORD ERROR" styleID="18" fgColor="008080" bgColor="FFFFFF" fontName="" fontStyle="0" fontSize="" />
        </LexerType>
        <LexerType name="cpp" desc="C++" ext="">
            <WordsStyle name="PREPROCESSOR" styleID="9" fgColor="804000" bgColor="FFFFFF" fontName="" fontStyle="0" fontSize="" />
            <WordsStyle name="DEFAULT" styleID="11" fgColor="000000" bgColor="FFFFFF" fontName="" fontStyle="0" fontSize="" />
            <WordsStyle name="INSTRUCTION WORD" styleID="5" fgColor="0000FF" bgColor="FFFFFF" fontName="" fontStyle="1" fontSize="" keywordClass="instre1" />
            <WordsStyle name="TYPE WORD" styleID="16" fgColor="8000FF" bgColor="FFFFFF" fontName="" fontStyle="0" fontSize="" keywordClass="type1" />
            <WordsStyle name="NUMBER" styleID="4" fgColor="FF8000" bgColor="FFFFFF" fontName="" fontStyle="0" fontSize="" />
            <WordsStyle name="STRING" styleID="6" fgColor="808080" bgColor="FFFFFF" fontName="" fontStyle="0" fontSize="" />
            <WordsStyle name="CHARACTER" styleID="7" fgColor="808080" bgColor="FFFFFF" fontName="" fontStyle="0" fontSize="" />
            <WordsStyle name="OPERATOR" styleID="10" fgColor="000080" bgColor="FFFFFF" fontName="" fontStyle="1" fontSize="" />
            <WordsStyle name="VERBATIM" styleID="13" fgColor="000000" bgColor="FFFFFF" fontName="" fontStyle="0" fontSize="" />
            <WordsStyle name="REGEX" styleID="14" fgColor="000000" bgColor="FFFFFF" fontName="" fontStyle="1" fontSize="" />
            <WordsStyle name="COMMENT" styleID="1" fgColor="008000" bgColor="FFFFFF" fontName="" fontStyle="0" fontSize="" />
            <WordsStyle name="COMMENT LINE" styleID="2" fgColor="008000" bgColor="FFFFFF" fontName="" fontStyle="0" fontSize="" />
            <WordsStyle name="COMMENT DOC" styleID="3" fgColor="008080" bgColor="FFFFFF" fontName="" fontStyle="0" fontSize="" />
            <WordsStyle name="COMMENT LINE DOC" styleID="15" fgColor="008080" bgColor="FFFFFF" fontName="" fontStyle="0" fontSize="" />
            <WordsStyle name="COMMENT DOC KEYWORD" styleID="17" fgColor="008080" bgColor="FFFFFF" fontName="" fontStyle="1" fontSize="" />
            <WordsStyle name="COMMENT DOC KEYWORD ERROR" styleID="18" fgColor="008080" bgColor="FFFFFF" fontName="" fontStyle="0" fontSize="" />
        </LexerType>
        <LexerType name="cs" desc="C#" ext="">
            <WordsStyle name="PREPROCESSOR" styleID="9" fgColor="804000" bgColor="FFFFFF" fontName="" fontStyle="0" fontSize="" />
            <WordsStyle name="DEFAULT" styleID="11" fgColor="000000" bgColor="FFFFFF" fontName="" fontStyle="0" fontSize="" />
            <WordsStyle name="INSTRUCTION WORD" styleID="5" fgColor="0000FF" bgColor="FFFFFF" fontName="" fontStyle="1" fontSize="" keywordClass="instre1" />
            <WordsStyle name="TYPE WORD" styleID="16" fgColor="8000FF" bgColor="FFFFFF" fontName="" fontStyle="0" fontSize="" />
            <WordsStyle name="NUMBER" styleID="4" fgColor="FF8000" bgColor="FFFFFF" fontName="" fontStyle="0" fontSize="" />
            <WordsStyle name="STRING" styleID="6" fgColor="808080" bgColor="FFFFFF" fontName="" fontStyle="0" fontSize="" />
            <WordsStyle name="CHARACTER" styleID="7" fgColor="808080" bgColor="FFFFFF" fontName="" fontStyle="0" fontSize="" />
            <WordsStyle name="OPERATOR" styleID="10" fgColor="000080" bgColor="FFFFFF" fontName="" fontStyle="1" fontSize="" />
            <WordsStyle name="VERBATIM" styleID="13" fgColor="000000" bgColor="FFFFFF" fontName="" fontStyle="0" fontSize="" />
            <WordsStyle name="REGEX" styleID="14" fgColor="000000" bgColor="FFFFFF" fontName="" fontStyle="1" fontSize="" />
            <WordsStyle name="COMMENT" styleID="1" fgColor="008000" bgColor="FFFFFF" fontName="" fontStyle="0" fontSize="" />
            <WordsStyle name="COMMENT LINE" styleID="2" fgColor="008000" bgColor="FFFFFF" fontName="" fontStyle="0" fontSize="" />
            <WordsStyle name="COMMENT DOC" styleID="3" fgColor="008080" bgColor="FFFFFF" fontName="" fontStyle="0" fontSize="" />
            <WordsStyle name="COMMENT LINE DOC" styleID="15" fgColor="008080" bgColor="FFFFFF" fontName="" fontStyle="0" fontSize="" />
            <WordsStyle name="COMMENT DOC KEYWORD" styleID="17" fgColor="008080" bgColor="FFFFFF" fontName="" fontStyle="1" fontSize="" />
            <WordsStyle name="COMMENT DOC KEYWORD ERROR" styleID="18" fgColor="008080" bgColor="FFFFFF" fontName="" fontStyle="0" fontSize="" />
        </LexerType>
        <LexerType name="css" desc="CSS" ext="">
            <WordsStyle name="DEFAULT" styleID="0" fgColor="000000" bgColor="FFFFFF" fontName="" fontStyle="0" fontSize="" />
            <WordsStyle name="TAG" styleID="1" fgColor="0000FF" bgColor="FFFFFF" fontName="Batang" fontStyle="0" fontSize="" />
            <WordsStyle name="CLASS" styleID="2" fgColor="FF0000" bgColor="FFFFFF" fontName="" fontStyle="0" fontSize="" />
            <WordsStyle name="PSEUDOCLASS" styleID="3" fgColor="FF8000" bgColor="FFFFFF" fontName="" fontStyle="1" fontSize="" />
            <WordsStyle name="UNKNOWN_PSEUDOCLASS" styleID="4" fgColor="FF8080" bgColor="FFFFFF" fontName="" fontStyle="0" fontSize="" />
            <WordsStyle name="OPERATOR" styleID="5" fgColor="000000" bgColor="FFFFFF" fontName="" fontStyle="1" fontSize="" />
            <WordsStyle name="IDENTIFIER" styleID="6" fgColor="8080C0" bgColor="FFFFFF" fontName="" fontStyle="1" fontSize="" keywordClass="instre1" />
            <WordsStyle name="UNKNOWN_IDENTIFIER" styleID="7" fgColor="000000" bgColor="FFFFFF" fontName="" fontStyle="0" fontSize="" />
            <WordsStyle name="VALUE" styleID="8" fgColor="000000" bgColor="FFFFFF" fontName="" fontStyle="1" fontSize="" />
            <WordsStyle name="COMMENT" styleID="9" fgColor="008000" bgColor="FFFFFF" fontName="" fontStyle="0" fontSize="" />
            <WordsStyle name="ID" styleID="10" fgColor="0080FF" bgColor="FFFFFF" fontName="" fontStyle="1" fontSize="" />
            <WordsStyle name="IMPORTANT" styleID="11" fgColor="FF0000" bgColor="FFFFFF" fontName="" fontStyle="1" fontSize="" />
            <WordsStyle name="DIRECTIVE" styleID="12" fgColor="0080FF" bgColor="FFFFFF" fontName="" fontStyle="0" fontSize="" />
        </LexerType>
        <LexerType name="html" desc="HTML" ext="">
            <WordsStyle name="DEFAULT" styleID="0" fgColor="000000" bgColor="FFFFFF" fontName="" fontStyle="1" fontSize="" />
            <WordsStyle name="COMMENT" styleID="9" fgColor="008000" bgColor="FFFFFF" fontName="" fontStyle="0" fontSize="" />
            <WordsStyle name="NUMBER" styleID="5" fgColor="FF0000" bgColor="FFFFFF" fontName="" fontStyle="0" fontSize="" />
            <WordsStyle name="DOUBLESTRING" styleID="6" fgColor="8000FF" bgColor="FFFFFF" fontName="" fontStyle="1" fontSize="" />
            <WordsStyle name="SINGLESTRING" styleID="7" fgColor="8000FF" bgColor="FFFFFF" fontName="" fontStyle="1" fontSize="" />
            <WordsStyle name="TAG" styleID="1" fgColor="0000FF" bgColor="FFFFFF" fontName="" fontStyle="0" fontSize="" />
            <WordsStyle name="TAGEND" styleID="11" fgColor="0000FF" bgColor="FFFFFF" fontName="" fontStyle="0" fontSize="" />
            <WordsStyle name="TAGUNKNOWN" styleID="2" fgColor="000000" bgColor="FFFFFF" fontName="" fontStyle="0" fontSize="" />
            <WordsStyle name="ATTRIBUTE" styleID="3" fgColor="FF0000" bgColor="FFFFFF" fontName="" fontStyle="0" fontSize="" />
            <WordsStyle name="ATTRIBUTEUNKNOWN" styleID="4" fgColor="000000" bgColor="FFFFFF" fontName="" fontStyle="0" fontSize="" />
            <WordsStyle name="SGMLDEFAULT" styleID="21" fgColor="000000" bgColor="A6CAF0" fontName="" fontStyle="0" fontSize="" />
            <WordsStyle name="CDATA" styleID="17" fgColor="FF8000" bgColor="FFFFFF" fontName="" fontStyle="0" fontSize="" />
            <WordsStyle name="VALUE" styleID="19" fgColor="FF8000" bgColor="FEFDE0" fontName="" fontStyle="0" fontSize="" />
            <WordsStyle name="ENTITY" styleID="10" fgColor="000000" bgColor="FEFDE0" fontName="" fontStyle="2" fontSize="" />
        </LexerType>
        <LexerType name="java" desc="Java" ext="">
            <WordsStyle name="PREPROCESSOR" styleID="9" fgColor="804000" bgColor="FFFFFF" fontName="" fontStyle="0" fontSize="" />
            <WordsStyle name="DEFAULT" styleID="11" fgColor="000000" bgColor="FFFFFF" fontName="" fontStyle="0" fontSize="" />
            <WordsStyle name="INSTRUCTION WORD" styleID="5" fgColor="0000FF" bgColor="FFFFFF" fontName="" fontStyle="1" fontSize="" keywordClass="instre1" />
            <WordsStyle name="TYPE WORD" styleID="16" fgColor="8000FF" bgColor="FFFFFF" fontName="" fontStyle="0" fontSize="" keywordClass="type1" />
            <WordsStyle name="NUMBER" styleID="4" fgColor="FF8000" bgColor="FFFFFF" fontName="" fontStyle="0" fontSize="" />
            <WordsStyle name="STRING" styleID="6" fgColor="808080" bgColor="FFFFFF" fontName="" fontStyle="0" fontSize="" />
            <WordsStyle name="CHARACTER" styleID="7" fgColor="808080" bgColor="FFFFFF" fontName="" fontStyle="0" fontSize="" />
            <WordsStyle name="OPERATOR" styleID="10" fgColor="000080" bgColor="FFFFFF" fontName="" fontStyle="1" fontSize="" />
            <WordsStyle name="VERBATIM" styleID="13" fgColor="000000" bgColor="FFFFFF" fontName="" fontStyle="0" fontSize="" />
            <WordsStyle name="REGEX" styleID="14" fgColor="000000" bgColor="FFFFFF" fontName="" fontStyle="1" fontSize="" />
            <WordsStyle name="COMMENT" styleID="1" fgColor="008000" bgColor="FFFFFF" fontName="" fontStyle="0" fontSize="" />
            <WordsStyle name="COMMENT LINE" styleID="2" fgColor="008000" bgColor="FFFFFF" fontName="" fontStyle="0" fontSize="" />
            <WordsStyle name="COMMENT DOC" styleID="3" fgColor="008080" bgColor="FFFFFF" fontName="" fontStyle="0" fontSize="" />
            <WordsStyle name="COMMENT LINE DOC" styleID="15" fgColor="008080" bgColor="FFFFFF" fontName="" fontStyle="0" fontSize="" />
            <WordsStyle name="COMMENT DOC KEYWORD" styleID="17" fgColor="008080" bgColor="FFFFFF" fontName="" fontStyle="1" fontSize="" />
            <WordsStyle name="COMMENT DOC KEYWORD ERROR" styleID="18" fgColor="008080" bgColor="FFFFFF" fontName="" fontStyle="0" fontSize="" />
        </LexerType>
        <LexerType name="javascript" desc="Javascript" ext="">
            <WordsStyle name="DEFAULT" styleID="41" fgColor="000000" bgColor="F2F4FF" fontName="" fontStyle="0" fontSize="" />
            <WordsStyle name="NUMBER" styleID="45" fgColor="FF0000" bgColor="F2F4FF" fontName="" fontStyle="0" fontSize="" />
            <WordsStyle name="WORD" styleID="46" fgColor="000000" bgColor="F2F4FF" fontName="" fontStyle="0" fontSize="" />
            <WordsStyle name="KEYWORD" styleID="47" fgColor="000080" bgColor="F2F4FF" fontName="" fontStyle="3" fontSize="" keywordClass="instre1" />
            <WordsStyle name="DOUBLESTRING" styleID="48" fgColor="808080" bgColor="F2F4FF" fontName="" fontStyle="0" fontSize="" />
            <WordsStyle name="SINGLESTRING" styleID="49" fgColor="808080" bgColor="F2F4FF" fontName="" fontStyle="0" fontSize="" />
            <WordsStyle name="SYMBOLS" styleID="50" fgColor="000000" bgColor="F2F4FF" fontName="" fontStyle="1" fontSize="" />
            <WordsStyle name="REGEX" styleID="52" fgColor="8000FF" bgColor="F2F4FF" fontName="" fontStyle="0" fontSize="" />
            <WordsStyle name="COMMENT" styleID="42" fgColor="008000" bgColor="F2F4FF" fontName="" fontStyle="0" fontSize="" />
            <WordsStyle name="COMMENTLINE" styleID="43" fgColor="008000" bgColor="F2F4FF" fontName="" fontStyle="0" fontSize="" />
            <WordsStyle name="COMMENTDOC" styleID="44" fgColor="008080" bgColor="F2F4FF" fontName="" fontStyle="0" fontSize="" />
        </LexerType>
        <LexerType name="php" desc="php" ext="">
            <WordsStyle name="QUESTION MARK" styleID="18" fgColor="FF0000" bgColor="FDF8E3" fontName="" fontStyle="0" fontSize="" />
            <WordsStyle name="DEFAULT" styleID="118" fgColor="000000" bgColor="FEFCF5" fontName="" fontStyle="0" fontSize="" />
            <WordsStyle name="STRING" styleID="119" fgColor="808080" bgColor="FEFCF5" fontName="" fontStyle="0" fontSize="" />
            <WordsStyle name="STRING VARIABLE" styleID="126" fgColor="808080" bgColor="FEFCF5" fontName="" fontStyle="1" fontSize="" />
            <WordsStyle name="SIMPLESTRING" styleID="120" fgColor="808080" bgColor="FEFCF5" fontName="" fontStyle="0" fontSize="" />
            <WordsStyle name="WORD" styleID="121" fgColor="0000FF" bgColor="FEFCF5" fontName="" fontStyle="1" fontSize="" keywordClass="instre1" />
            <WordsStyle name="NUMBER" styleID="122" fgColor="FF8000" bgColor="FEFCF5" fontName="" fontStyle="0" fontSize="" />
            <WordsStyle name="VARIABLE" styleID="123" fgColor="000080" bgColor="FEFCF5" fontName="" fontStyle="0" fontSize="" />
            <WordsStyle name="COMMENT" styleID="124" fgColor="008000" bgColor="FEFCF5" fontName="" fontStyle="0" fontSize="" />
            <WordsStyle name="COMMENTLINE" styleID="125" fgColor="008000" bgColor="FEFCF5" fontName="" fontStyle="0" fontSize="" />
            <WordsStyle name="OPERATOR" styleID="127" fgColor="8000FF" bgColor="FEFCF5" fontName="" fontStyle="0" fontSize="" />
        </LexerType>
        <LexerType name="ruby" desc="Ruby" ext="">
            <WordsStyle name="DEFAULT" styleID="0" fgColor="000000" bgColor="FFFFFF" fontName="" fontStyle="0" fontSize="" />
            <WordsStyle name="ERROR" styleID="1" fgColor="000000" bgColor="FFFFFF" fontName="" fontStyle="0" fontSize="" />
            <WordsStyle name="COMMENTLINE" styleID="2" fgColor="008000" bgColor="FFFFFF" fontName="" fontStyle="0" fontSize="" />
            <WordsStyle name="POD" styleID="3" fgColor="004000" bgColor="C0FFC0" fontName="" fontStyle="0" fontSize="" />
            <WordsStyle name="NUMBER" styleID="4" fgColor="FF8000" bgColor="FFFFFF" fontName="" fontStyle="0" fontSize="" />
            <WordsStyle name="INSTRUCTION" styleID="5" fgColor="0000FF" bgColor="FFFFFF" fontName="" fontStyle="1" fontSize="" keywordClass="instre1" />
            <WordsStyle name="STRING" styleID="6" fgColor="808080" bgColor="FFFFFF" fontName="" fontStyle="0" fontSize="" />
            <WordsStyle name="CHARACTER" styleID="7" fgColor="808000" bgColor="FFFFFF" fontName="" fontStyle="0" fontSize="" />
            <WordsStyle name="CLASS NAME" styleID="8" fgColor="0080C0" bgColor="FFFFFF" fontName="" fontStyle="1" fontSize="" />
            <WordsStyle name="DEF NAME" styleID="9" fgColor="8080FF" bgColor="FFFFCC" fontName="" fontStyle="1" fontSize="" />
            <WordsStyle name="OPERATOR" styleID="10" fgColor="000080" bgColor="FFFFFF" fontName="" fontStyle="1" fontSize="" />
            <WordsStyle name="IDENTIFIER" styleID="11" fgColor="000000" bgColor="FFFFFF" fontName="" fontStyle="0" fontSize="" />
            <WordsStyle name="REGEX" styleID="12" fgColor="0080FF" bgColor="FFFFFF" fontName="" fontStyle="0" fontSize="" />
            <WordsStyle name="GLOBAL" styleID="13" fgColor="000080" bgColor="FFFFFF" fontName="" fontStyle="1" fontSize="" />
            <WordsStyle name="SYMBOL" styleID="14" fgColor="000000" bgColor="FFFFFF" fontName="" fontStyle="0" fontSize="" />
            <WordsStyle name="MODULE NAME" styleID="15" fgColor="804000" bgColor="FFFFFF" fontName="" fontStyle="1" fontSize="" />
            <WordsStyle name="INSTANCE VAR" styleID="16" fgColor="000000" bgColor="FFFFFF" fontName="" fontStyle="0" fontSize="" />
            <WordsStyle name="CLASS VAR" styleID="17" fgColor="000000" bgColor="FFFFFF" fontName="" fontStyle="0" fontSize="" />
            <WordsStyle name="BACKTICKS" styleID="18" fgColor="FFFF00" bgColor="A08080" fontName="" fontStyle="0" fontSize="" />
            <WordsStyle name="DATA SECTION" styleID="19" fgColor="600000" bgColor="FFF0D8" fontName="" fontStyle="0" fontSize="" />
            <WordsStyle name="STRING Q" styleID="24" fgColor="808080" bgColor="FFFFFF" fontName="" fontStyle="0" fontSize="" />
        </LexerType>
        <LexerType name="xml" desc="XML" ext="">
            <WordsStyle name="XMLSTART" styleID="12" fgColor="FF0000" bgColor="FFFF00" fontName="" fontStyle="0" fontSize="" />
            <WordsStyle name="XMLEND" styleID="13" fgColor="FF0000" bgColor="FFFF00" fontName="" fontStyle="0" fontSize="" />
            <WordsStyle name="DEFAULT" styleID="0" fgColor="000000" bgColor="FFFFFF" fontName="" fontStyle="1" fontSize="" />
            <WordsStyle name="COMMENT" styleID="9" fgColor="008000" bgColor="FFFFFF" fontName="" fontStyle="0" fontSize="" />
            <WordsStyle name="NUMBER" styleID="5" fgColor="FF0000" bgColor="FFFFFF" fontName="" fontStyle="0" fontSize="" />
            <WordsStyle name="DOUBLESTRING" styleID="6" fgColor="8000FF" bgColor="FFFFFF" fontName="" fontStyle="1" fontSize="" />
            <WordsStyle name="SINGLESTRING" styleID="7" fgColor="8000FF" bgColor="FFFFFF" fontName="" fontStyle="1" fontSize="" />
            <WordsStyle name="TAG" styleID="1" fgColor="0000FF" bgColor="FFFFFF" fontName="" fontStyle="0" fontSize="" />
            <WordsStyle name="TAGEND" styleID="11" fgColor="0000FF" bgColor="FFFFFF" fontName="" fontStyle="0" fontSize="" />
            <WordsStyle name="TAGUNKNOWN" styleID="2" fgColor="0000FF" bgColor="FFFFFF" fontName="" fontStyle="0" fontSize="" />
            <WordsStyle name="ATTRIBUTE" styleID="3" fgColor="FF0000" bgColor="FFFFFF" fontName="" fontStyle="0" fontSize="" />
            <WordsStyle name="ATTRIBUTEUNKNOWN" styleID="4" fgColor="FF0000" bgColor="FFFFFF" fontName="" fontStyle="0" fontSize="" />
            <WordsStyle name="SGMLDEFAULT" styleID="21" fgColor="000000" bgColor="A6CAF0" fontName="" fontStyle="0" fontSize="" />
            <WordsStyle name="CDATA" styleID="17" fgColor="FF8000" bgColor="FFFFFF" fontName="" fontStyle="0" fontSize="" />
        </LexerType>
        <LexerType name="searchResult" desc="Search result" ext="">
            <WordsStyle name="Search Header" styleID="1" fgColor="000080" bgColor="BBBBFF" fontName="" fontStyle="1" fontSize="" />
            <WordsStyle name="File Header" styleID="2" fgColor="008000" bgColor="D5FFD5" fontName="" fontStyle="1" fontSize="" />
            <WordsStyle name="Line Number" styleID="3" fgColor="000000" bgColor="FFFFFF" fontName="" fontStyle="0" fontSize="" />
            <WordsStyle name="Hit Word" styleID="4" fgColor="FF0000" bgColor="FFFFBF" fontName="" fontStyle="0" fontSize="" />
            <WordsStyle name="Selected Line" styleID="5" fgColor="000080" bgColor="FFFF4F" fontName="" fontStyle="0" fontSize="" />
            <WordsStyle name="Current line background colour" styleID="6" bgColor="E8E8FF" />
        </LexerType>
    </LexerStyles>
    <GlobalStyles>
        <!-- Attention : Don't modify the name of styleID="0" -->
        <WidgetStyle name="Global override" styleID="0" fgColor="FFFF80" bgColor="FF8000" fontName="Courier New" fontStyle="0" fontSize="10" />
        <WidgetStyle name="Default Style" styleID="32" fgColor="000000" bgColor="FFFFFF" fontName="Courier New" fontStyle="0" fontSize="10" />
        <WidgetStyle name="Indent guideline style" styleID="37" fgColor="C0C0C0" bgColor="FFFFFF" fontName="" fontStyle="0" fontSize="" />
        <WidgetStyle name="Brace highlight style" styleID="34" fgColor="FF0000" bgColor="FFFFFF" fontName="" fontStyle="1" fontSize="12" />
        <WidgetStyle name="Bad brace colour" styleID="35" fgColor="800000" bgColor="FFFFFF" fontName="" fontStyle="0" fontSize="" />
        <WidgetStyle name="Current line background colour" styleID="0" bgColor="E8E8FF" />
        <WidgetStyle name="Selected text colour" styleID="0" bgColor="C0C0C0" />
        <WidgetStyle name="Caret colour" styleID="2069" fgColor="8000FF" />
        <WidgetStyle name="Edge colour" styleID="0" fgColor="80FFFF" />
        <WidgetStyle name="Line number margin" styleID="33" fgColor="808080" bgColor="E4E4E4" fontName="" fontStyle="0" fontSize="" />
        <WidgetStyle name="Fold" styleID="0" fgColor="808080" bgColor="F3F3F3" />
        <WidgetStyle name="Fold active" styleID="0" fgColor="FF0000" />
        <WidgetStyle name="Fold margin" styleID="0" fgColor="FFFFFF" bgColor="E9E9E9" />
        <WidgetStyle name="White space symbol" styleID="0" fgColor="FFB56A" />
        <WidgetStyle name="Smart HighLighting" styleID="29" bgColor="00FF00" />
        <WidgetStyle name="Find Mark Style" styleID="31" bgColor="FF0000" />
        <WidgetStyle name="Mark Style 1" styleID="25" bgColor="00FFFF" />
        <WidgetStyle name="Mark Style 2" styleID="24" bgColor="FF8000" />
        <WidgetStyle name="Mark Style 3" styleID="23" bgColor="FFFF00" />
        <WidgetStyle name="Mark Style 4" styleID="22" bgColor="8000FF" />
        <WidgetStyle name="Mark Style 5" styleID="21" bgColor="008000" />
        <WidgetStyle name="Incremental highlight all" styleID="28" bgColor="0080FF" />
        <WidgetStyle name="Tags match highlighting" styleID="27" bgColor="8000FF" />
        <WidgetStyle name="Tags attribute" styleID="26" bgColor="FFFF00" />
        <WidgetStyle name="Active tab focused indicator" styleID="0" fgColor="FAAA3C" />
        <WidgetStyle name="Active tab unfocused indicator" styleID="0" fgColor="FFCAB0" />
        <WidgetStyle name="Active tab text" styleID="0" fgColor="000000" />
        <WidgetStyle name="Inactive tabs" styleID="0" fgColor="808080" bgColor="C0C0C0" />
        <WidgetStyle name="URL hovered" styleID="0" fgColor="0000FF" />
    </GlobalStyles>
</NotepadPlus>
